django_utils/__about__.py
django_utils/__init__.py
django_utils/base_models.py
django_utils/choices.py
django_utils/fields.py
django_utils/models.py
django_utils/queryset.py
django_utils/utils.py
django_utils/view_decorators.py
django_utils/views.py
django_utils/admin/__init__.py
django_utils/admin/filters.py
django_utils/management/__init__.py
django_utils/management/commands/__init__.py
django_utils/management/commands/admin_autogen.py
django_utils/management/commands/base_command.py
django_utils/management/commands/settings.py
django_utils/templates/base.html
django_utils/templates/django_utils/base.html
django_utils/templates/django_utils/error_400.html
django_utils/templates/django_utils/error_403.html
django_utils/templates/django_utils/error_404.html
django_utils/templates/django_utils/error_500.html
django_utils/templates/django_utils/admin/dropdown_filter.html
django_utils/templates/django_utils/admin/select2_filter.html
django_utils/templatetags/__init__.py
django_utils/templatetags/debug.py
django_utils2-3.0.2.dist-info/METADATA
django_utils2-3.0.2.dist-info/WHEEL
django_utils2-3.0.2.dist-info/top_level.txt
django_utils2-3.0.2.dist-info/RECORD
