Metadata-Version: 2.1
Name: django-utils2
Version: 3.0.2
Summary: Django Utils is a module with some convenient utilities not included with the standard Django install
Home-page: https://github.com/WoLpH/django-utils
Author: Rick van Hattem
Author-email: Rick.van.Hattem@Fawo.nl
License: BSD
Classifier: Development Status :: 6 - Mature
Classifier: Environment :: Web Environment
Classifier: Framework :: Django
Classifier: Intended Audience :: Developers
Classifier: License :: OSI Approved :: BSD License
Classifier: Operating System :: OS Independent
Classifier: Natural Language :: English
Classifier: Programming Language :: Python
Classifier: Programming Language :: Python :: 2
Classifier: Programming Language :: Python :: 2.7
Classifier: Programming Language :: Python :: 3
Classifier: Programming Language :: Python :: 3.4
Classifier: Programming Language :: Python :: 3.5
Classifier: Programming Language :: Python :: 3.6
Classifier: Programming Language :: Python :: 3.7
Classifier: Topic :: Internet :: WWW/HTTP
Classifier: Topic :: Internet :: WWW/HTTP :: Dynamic Content
Classifier: Topic :: Internet :: WWW/HTTP :: WSGI
Classifier: Topic :: Software Development :: Libraries :: Python Modules
Requires-Dist: python-utils>=3.5.2
Provides-Extra: docs
Requires-Dist: django; extra == "docs"
Requires-Dist: mock; extra == "docs"
Requires-Dist: sphinx>=1.7.2; extra == "docs"
Provides-Extra: tests
Requires-Dist: sphinx; extra == "tests"
Requires-Dist: pytest; extra == "tests"
Requires-Dist: pytest-cache; extra == "tests"
Requires-Dist: pytest-cov; extra == "tests"
Requires-Dist: pytest-django; extra == "tests"
Requires-Dist: jinja2; extra == "tests"
Requires-Dist: pygments; extra == "tests"
